LICENSE
MANIFEST.in
README.rst
pyproject.toml
setup.cfg
setup.py
adbus/__init__.py
adbus/__version__.py
adbus/datatypes.py
adbus/exceptions.py
adbus/sdbus.c
adbus/sdbus.pyx
adbus/sdbus_h.pxd
adbus/service.py
adbus.egg-info/PKG-INFO
adbus.egg-info/SOURCES.txt
adbus.egg-info/dependency_links.txt
adbus.egg-info/top_level.txt
adbus/client/__init__.py
adbus/client/call.py
adbus/client/getset.py
adbus/client/listen.py
adbus/client/proxy.py
adbus/sdbus/call.pxi
adbus/sdbus/error.pxi
adbus/sdbus/listen.pxi
adbus/sdbus/manager.pxi
adbus/sdbus/message.pxi
adbus/sdbus/method.pxi
adbus/sdbus/object.pxi
adbus/sdbus/property.pxi
adbus/sdbus/service.pxi
adbus/sdbus/signal.pxi
adbus/sdbus/signature.pxi
adbus/sdbus/snake.pxi
adbus/server/__init__.py
adbus/server/method.py
adbus/server/object.py
adbus/server/property.py
adbus/server/signal.py
tests/test_client.py
tests/test_sdbus_signature.py
tests/test_sdbus_snake.py
tests/test_server.py