Metadata-Version: 2.1
Name: adbus
Version: 1.2.7
Summary: asyncio based dbus interface
Home-page: https://github.com/ccxtechnologies/adbus
Download-URL: https://github.com/ccxtechnologies/archive/v1.2.7.tar.gz
Author: CCX Technologies
Author-email: charles@ccxtechnologies.com
License: MIT
Requires-Python: >=3.7
License-File: LICENSE
